conda_rocker/__init__.py
conda_rocker/conda_extension.py
conda_rocker/templates/conda_snippet.Dockerfile
conda_rocker/templates/conda_user_snippet.Dockerfile
conda_rocker-0.0.3.dist-info/METADATA
conda_rocker-0.0.3.dist-info/WHEEL
conda_rocker-0.0.3.dist-info/entry_points.txt
conda_rocker-0.0.3.dist-info/licenses/LICENSE
conda_rocker-0.0.3.dist-info/RECORD
